grunnlag/__init__.py
grunnlag/extenders.py
grunnlag/graphql/mutations/experiment.py
grunnlag/graphql/mutations/metric.py
grunnlag/graphql/mutations/representation.py
grunnlag/graphql/mutations/sample.py
grunnlag/graphql/queries/experiment.py
grunnlag/graphql/queries/metric.py
grunnlag/graphql/queries/representation.py
grunnlag/graphql/queries/sample.py
grunnlag/managers.py
grunnlag/schema.py
grunnlag-0.4.22.dist-info/WHEEL
grunnlag-0.4.22.dist-info/METADATA
grunnlag-0.4.22.dist-info/RECORD
