Metadata-Version: 2.1
Name: grunnlag
Version: 0.4.22
Summary: Basic Schema for interacting with Arnheim through Bergen
Home-page: https://github.com/jhnnsrs/grunnlag
License: CC BY-NC 3.0
Author: jhnnsrs
Author-email: jhnnsrs@gmail.com
Requires-Python: >=3.6.1,<4.0.0
Classifier: License :: Other/Proprietary License
Classifier: Programming Language :: Python :: 3
Classifier: Programming Language :: Python :: 3.7
Classifier: Programming Language :: Python :: 3.8
Classifier: Programming Language :: Python :: 3.9
Requires-Dist: bergen (>=0.4.69,<0.5.0)
Requires-Dist: dask[array,dataframe] (>=2020.12.0,<2021.0.0)
Requires-Dist: s3fs (>=0.6.0,<0.7.0); python_version >= "3.8" and python_version < "4.0"
Requires-Dist: s3fs (>=2021.5.0,<2022.0.0); python_version >= "3.6" and python_version < "4.0"
Requires-Dist: xarray (>=0.16.2,<0.17.0)
Requires-Dist: zarr (>=2.6.1,<3.0.0)
